paneltree_helloworld/__init__.py
paneltree_helloworld/main.py
paneltree_helloworld-0.1.3.dist-info/licenses/LICENSE
paneltree_helloworld-0.1.3.dist-info/METADATA
paneltree_helloworld-0.1.3.dist-info/WHEEL
paneltree_helloworld-0.1.3.dist-info/top_level.txt
paneltree_helloworld-0.1.3.dist-info/RECORD
