Metadata-Version: 2.4
Name: paneltree-helloworld
Version: 0.1.3
Summary: A simple Hello World package
Author-email: paneltree <paneltree@outlook.com>
License: MIT License
Classifier: Programming Language :: Python :: 3
Classifier: License :: OSI Approved :: MIT License
Classifier: Operating System :: OS Independent
Requires-Python: >=3.6
License-File: LICENSE
Dynamic: license-file
